{
    "key": "group_58210f73996fd",
    "title": "Tour Fields",
    "fields": [
        {
            "key": "field_58210f8eca55c",
            "label": "Duration",
            "name": "duration",
            "type": "text",
            "instructions": "",
            "required": 0,
            "conditional_logic": 0,
            "wrapper": {
                "width": "",
                "class": "",
                "id": ""
            },
            "default_value": "",
            "placeholder": "",
            "prepend": "",
            "append": "",
            "maxlength": "",
            "readonly": 0,
            "disabled": 0
        },
        {
            "key": "field_58210ff5ca55d",
            "label": "Prices",
            "name": "prices",
            "type": "repeater",
            "instructions": "Provided prices per number of tourists",
            "required": 0,
            "conditional_logic": 0,
            "wrapper": {
                "width": "",
                "class": "",
                "id": ""
            },
            "collapsed": "",
            "min": "",
            "max": "",
            "layout": "table",
            "button_label": "Add Block",
            "sub_fields": [
                {
                    "key": "field_58211025ca55e",
                    "label": "Number of tourists",
                    "name": "number_of_tourists",
                    "type": "number",
                    "instructions": "",
                    "required": 0,
                    "conditional_logic": 0,
                    "wrapper": {
                        "width": "",
                        "class": "",
                        "id": ""
                    },
                    "default_value": "",
                    "placeholder": "",
                    "prepend": "",
                    "append": "",
                    "min": 1,
                    "max": "",
                    "step": 1,
                    "readonly": 0,
                    "disabled": 0
                },
                {
                    "key": "field_58211042ca55f",
                    "label": "Price",
                    "name": "price",
                    "type": "number",
                    "instructions": "",
                    "required": 0,
                    "conditional_logic": 0,
                    "wrapper": {
                        "width": "",
                        "class": "",
                        "id": ""
                    },
                    "default_value": "",
                    "placeholder": "",
                    "prepend": "€",
                    "append": "",
                    "min": "",
                    "max": "",
                    "step": "",
                    "readonly": 0,
                    "disabled": 0
                }
            ]
        }
    ],
    "location": [
        [
            {
                "param": "post_type",
                "operator": "==",
                "value": "tours"
            }
        ]
    ],
    "menu_order": 0,
    "position": "normal",
    "style": "default",
    "label_placement": "top",
    "instruction_placement": "label",
    "hide_on_screen": "",
    "active": 1,
    "description": "",
    "modified": 1478651559
}